rum_auto_sender/__init__.py
rum_auto_sender/auto_sender.py
rum_auto_sender-0.1.3.dist-info/LICENSE
rum_auto_sender-0.1.3.dist-info/METADATA
rum_auto_sender-0.1.3.dist-info/WHEEL
rum_auto_sender-0.1.3.dist-info/top_level.txt
rum_auto_sender-0.1.3.dist-info/RECORD
