Metadata-Version: 2.1
Name: rum-auto-sender
Version: 0.1.3
Summary: auto sender for local dirpath to rum group
Home-page: https://github.com/liujuanjuan1984/auto_sender
Author: liujuanjuan1984
Author-email: qiaoanlu@163.com
Project-URL: Github Repo, https://github.com/liujuanjuan1984/auto_sender
Project-URL: Bug Tracker, https://github.com/liujuanjuan1984/auto_sender/issues
Project-URL: About Quorum, https://github.com/rumsystem/quorum
Keywords: mininode,rumsystem,quorum
Classifier: Programming Language :: Python :: 3
Classifier: Programming Language :: Python :: 3.8
Classifier: License :: OSI Approved :: GNU General Public License v3 (GPLv3)
Classifier: Operating System :: OS Independent
Requires-Python: >=3.8
License-File: LICENSE
Requires-Dist: mininode
